LICENSE.txt
MANIFEST.in
README.md
pyproject.toml
tox.ini
docs/code-of-conduct.md
docs/conf.py
docs/contributing.md
docs/getting-started.md
docs/index.rst
docs/plugin-module.rst
docs/requirements.txt
docs/_static/css/custom.css
src/danoan/word_def/plugins/modules/multilanguage_chatgpt.py
src/word_def_plugin_multilanguage_chatgpt.egg-info/PKG-INFO
src/word_def_plugin_multilanguage_chatgpt.egg-info/SOURCES.txt
src/word_def_plugin_multilanguage_chatgpt.egg-info/dependency_links.txt
src/word_def_plugin_multilanguage_chatgpt.egg-info/requires.txt
src/word_def_plugin_multilanguage_chatgpt.egg-info/top_level.txt