Metadata-Version: 2.1
Name: word-def-plugin-multilanguage-chatgpt
Version: 0.2.0
Summary: Multilanguage plugin for word-def
Author-email: Daniel Martins Antunes <danoan2008@gmail.com>
License: MIT License
Project-URL: Documentation, https://github.com/danoan/word-def-plugin-multilanguage-chatgpt#readme
Project-URL: Issues, https://github.com/danoan/word-def-plugin-multilanguage-chatgpt
Project-URL: Source, https://github.com/danoan/word-def-plugin-multilanguage-chatgpt
Classifier: Development Status :: 4 - Beta
Classifier: Programming Language :: Python
Classifier: Programming Language :: Python :: 3.8
Classifier: Programming Language :: Python :: Implementation :: CPython
Classifier: Programming Language :: Python :: Implementation :: PyPy
Requires-Python: >=3.8
License-File: LICENSE.txt
Requires-Dist: word-def<1.0.0,>=0.2.0
Requires-Dist: word-guru<1.0.0,>=0.1.0
